paconn/__init__.py
paconn/__main__.py
paconn/completer.py
paconn/apimanager/__init__.py
paconn/apimanager/apimanager.py
paconn/apimanager/apimanagerbuilder.py
paconn/apimanager/fileuploader.py
paconn/apimanager/flowrp.py
paconn/apimanager/flowrpbuilder.py
paconn/apimanager/powerappsrp.py
paconn/apimanager/powerappsrpbuilder.py
paconn/authentication/__init__.py
paconn/authentication/auth.py
paconn/authentication/profile.py
paconn/authentication/tokenmanager.py
paconn/commands/__init__.py
paconn/commands/commands.py
paconn/commands/create.py
paconn/commands/download.py
paconn/commands/help.py
paconn/commands/login.py
paconn/commands/logout.py
paconn/commands/params.py
paconn/commands/update.py
paconn/commands/validate.py
paconn/common/__init__.py
paconn/common/prompts.py
paconn/common/util.py
paconn/config/__init__.py
paconn/config/cli.flake8
paconn/operations/__init__.py
paconn/operations/download.py
paconn/operations/json_keys.py
paconn/operations/upsert.py
paconn/operations/validate.py
paconn/settings/__init__.py
paconn/settings/settings.py
paconn/settings/settingsbuilder.py
paconn/settings/settingsserializer.py
paconn/settings/util.py
paconn-0.0.21.dist-info/LICENSE
paconn-0.0.21.dist-info/METADATA
paconn-0.0.21.dist-info/WHEEL
paconn-0.0.21.dist-info/entry_points.txt
paconn-0.0.21.dist-info/top_level.txt
paconn-0.0.21.dist-info/RECORD
