Metadata-Version: 2.1
Name: paconn
Version: 0.0.21
Summary: Microsoft Power Platform Connectors CLI
Author: Microsoft Corporation
Author-email: connectors@microsoft.com
License: MIT
Keywords: azure,powerapps,flow,power platform,connectors
Classifier: Development Status :: 4 - Beta
Classifier: Intended Audience :: Developers
Classifier: Topic :: Software Development :: Build Tools
Classifier: Environment :: Console
Classifier: License :: OSI Approved :: MIT License
Classifier: Natural Language :: English
Classifier: Programming Language :: Python :: 3.5
Classifier: Programming Language :: Python :: 3.6
Requires-Python: >=3.5,<4
License-File: LICENSE
Requires-Dist: docutils
Requires-Dist: flake8
Requires-Dist: future
Requires-Dist: knack (~=0.5.1)
Requires-Dist: pytest
Requires-Dist: pytest-xdist
Requires-Dist: virtualenv
Requires-Dist: requests
Requires-Dist: adal
Requires-Dist: msrestazure
Requires-Dist: azure-storage-blob (<12.0,>=2.1)
Requires-Dist: pylint (~=1.9.2) ; python_version<'3.0'
Requires-Dist: pylint (~=2.0.0) ; python_version>='3.0'
